[
    {
        "code": 19956512,
        "name": " CARLOS ANTONIO JIMÉNEZ PERAZA",
        "voted": false
    },
    {
        "code": 19956513,
        "name": " JEFFRY ANTONIO SOSA RIVERA",
        "voted": false
    },
    {
        "code": 4700839,
        "name": " ROBERTO CARLOS RODRÍGUEZ NÚÑEZ",
        "voted": false
    },
    {
        "code": 19866121,
        "name": " EMELY SAMARIA ROMERO HERNÁNDEZ",
        "voted": false
    },
    {
        "code": 19948176,
        "name": " HELEN DAYANA GONZALEZ LEMUS",
        "voted": false
    },
    {
        "code": 19844321,
        "name": " HELLEN ESTEFANY SALVADOR TEJADA",
        "voted": false
    },
    {
        "code": 19926922,
        "name": " ANGEL GUSTAVO LANDAVERDE REYES",
        "voted": false
    },
    {
        "code": 19926925,
        "name": " HECTOR AMILCAR LANDAVERDE",
        "voted": false
    },
    {
        "code": 19826944,
        "name": " SELENA ABIGAIL MEJIA AGUILAR",
        "voted": false
    },
    {
        "code": 3671151,
        "name": " JENNIFER ABIGAIL VALLE GUARDADO",
        "voted": false
    },
    {
        "code": 20029987,
        "name": " MICHAEL ALEJANDRO MARTINEZ LEMUS",
        "voted": false
    },
    {
        "code": 19852670,
        "name": " KEIRY ADRIANA AREVALO VILLANUEVA",
        "voted": false
    },
    {
        "code": 19919970,
        "name": " RUBEN FABRICIO BAIRES CALDERON",
        "voted": false
    },
    {
        "code": 19948180,
        "name": " CHRISTIAN JOSUE DAMAS MANCIA",
        "voted": false
    },
    {
        "code": 19948181,
        "name": " ANGIE ALEXIA DIAZ ALVARADO",
        "voted": false
    },
    {
        "code": 19948182,
        "name": " JOSUE DANIEL FUENTES PORTILLO",
        "voted": false
    },
    {
        "code": 19948183,
        "name": " JOSUÉ DAVID HERNÁNDEZ MEJÍA",
        "voted": false
    },
    {
        "code": 19948187,
        "name": " MEILIN ADILENE MORALES LANDAVERDE",
        "voted": false
    },
    {
        "code": 19948189,
        "name": " ROSA ESTEFANY REGALADO OSEGUEDA",
        "voted": false
    },
    {
        "code": 19948190,
        "name": " FABIOLA ANGELIE SALVADOR OSEGUEDA",
        "voted": false
    },
    {
        "code": 19948188,
        "name": " STEVEN ALESSANDRO PORTILLO PÉREZ",
        "voted": false
    },
    {
        "code": 19948186,
        "name": " LOURDES DEL CARMEN MANCIA CARVAJAL",
        "voted": false
    },
    {
        "code": 5335917,
        "name": " ANGÉLICA LISSETH ABREGO SOLÓRZANO",
        "voted": false
    },
    {
        "code": 5335918,
        "name": " ROBERTO ALEXANDER GARCÍA MURCIA",
        "voted": false
    },
    {
        "code": 5335911,
        "name": " ROSA LIDIA MARTÍNEZ MEJÍA",
        "voted": false
    },
    {
        "code": 5335914,
        "name": " ELISEO ADONAY MENJÍVAR CÓRDOVA",
        "voted": false
    },
    {
        "code": 5335915,
        "name": " ZAIRA NAHOMY PORTILLO MURCIA",
        "voted": false
    },
    {
        "code": 5335931,
        "name": " SONIA MARISOL PÉREZ ALAS",
        "voted": false
    },
    {
        "code": 6867222,
        "name": " LEYDI ESTEFANY DÍAZ CARDOZA",
        "voted": false
    },
    {
        "code": 6337749,
        "name": " LUIS DAVID SÁNCHEZ RAMÍREZ",
        "voted": false
    },
    {
        "code": 5868959,
        "name": " RICARDO EMILIO PERALTA DIAZ",
        "voted": false
    },
    {
        "code": 6652221,
        "name": " OSCAR BLADIMIR PÉREZ LINARES",
        "voted": false
    },
    {
        "code": 19948175,
        "name": " SAMUEL ISAI FUENTES HENRÍQUEZ",
        "voted": false
    },
    {
        "code": 20154334,
        "name": " FABIO ALEJANDRO CARDOZA ROMERO",
        "voted": false
    },
    {
        "code": 20032705,
        "name": " JEANESY MICHELLE ORELLANA DÍAZ",
        "voted": false
    },
    {
        "code": 20051075,
        "name": " ELÍAS EZEQUIEL SÁNCHEZ RAMÍREZ",
        "voted": false
    },
    {
        "code": 20051076,
        "name": " JAVIER STEVEN VILLALTA GUTIÉRREZ",
        "voted": false
    },
    {
        "code": 20067397,
        "name": " JUAN CARLOS IBÁÑEZ PÉREZ",
        "voted": false
    },
    {
        "code": 20169522,
        "name": " DANIEL ERNESTO CÓRDOVA MEJÍA",
        "voted": false
    },
    {
        "code": 20118598,
        "name": " NALLELY ESTEFANY GONZÁLEZ RAMÍREZ",
        "voted": false
    },
    {
        "code": 20118983,
        "name": " DAYANA NICOLE PÉREZ HUEZO",
        "voted": false
    },
    {
        "code": 20118984,
        "name": " DANIELA ARELY SALGUERO BAIRES",
        "voted": false
    },
    {
        "code": 20118985,
        "name": " PABLO IVÁN SALGUERO MURCIA",
        "voted": false
    },
    {
        "code": 20118987,
        "name": " FLOR ENEYDA DERAS HERNÁNDEZ",
        "voted": false
    },
    {
        "code": 20118988,
        "name": " ALBERTO ANTONIO DERAS LEMUS",
        "voted": false
    },
    {
        "code": 20118990,
        "name": " MARÍA CRISTINA GUEVARA DERAS",
        "voted": false
    },
    {
        "code": 20118991,
        "name": " OSMIN EDENILSON HERNANDEZ ALBERTO",
        "voted": false
    },
    {
        "code": 20118992,
        "name": " ANTHONY GABRIEL HERNÁNDEZ CALLEJAS",
        "voted": false
    },
    {
        "code": 20118993,
        "name": " KAREN ABIGAIL HUEZO OSEGUEDA",
        "voted": false
    },
    {
        "code": 20118996,
        "name": " MARISOL ABIGAIL OCHOA MOLINA",
        "voted": false
    },
    {
        "code": 20118997,
        "name": " KIMBERLY ELIZABETH PÉREZ VILLANUEVA",
        "voted": false
    },
    {
        "code": 20118999,
        "name": " JUAN DIEGO SOLÓRZANO ALVARADO",
        "voted": false
    },
    {
        "code": 20119000,
        "name": " MERARY ISAMAR VASQUEZ HENRIQUEZ",
        "voted": false
    },
    {
        "code": 20118994,
        "name": " ARMANDO EFRAÍN MEJÍA CASCO",
        "voted": false
    },
    {
        "code": 20184092,
        "name": " RICARDO ALEXANDER SOLÒRZANO RECINOS",
        "voted": false
    },
    {
        "code": 20194491,
        "name": " CRISTHIAN ERNESTO MARTÍNEZ VÁSQUEZ",
        "voted": false
    },
    {
        "code": 20192782,
        "name": " ALEJANDRO ENMANUEL PERALTA DIAZ",
        "voted": false
    },
    {
        "code": 20275525,
        "name": " JONATHAN WILFREDO LÓPEZ LANDAVERDE",
        "voted": false
    },
    {
        "code": 20275433,
        "name": " XIOMARA MARICELA GALÁN LÓPEZ",
        "voted": false
    },
    {
        "code": 20275434,
        "name": " MARIA ISABEL HUEZO LANDAVERDE",
        "voted": false
    },
    {
        "code": 20275435,
        "name": " EMELY VANESSA MURCIA ALAS",
        "voted": false
    },
    {
        "code": 20275479,
        "name": " DANIELA JOHANA LANDAVERDE GUILLÉN",
        "voted": false
    },
    {
        "code": 20275481,
        "name": " MARJORIE DANIELA MORALES LANDAVERDE",
        "voted": false
    },
    {
        "code": 20275483,
        "name": " MADELYN NALLELY OCHOA ALFARO",
        "voted": false
    },
    {
        "code": 20275484,
        "name": " RUTH SARAÍ PÉREZ MARTÍNEZ",
        "voted": false
    },
    {
        "code": 20275488,
        "name": " JOSÉ DANIEL RIVERA MÉNDEZ",
        "voted": false
    },
    {
        "code": 20275489,
        "name": " LISSETH ALEXANDRA VALLE GUARDADO",
        "voted": false
    },
    {
        "code": 20275490,
        "name": " GUILLERMO RIQUELMI VÁSQUEZ MENA",
        "voted": false
    },
    {
        "code": 20275516,
        "name": " JOSE ALEJANDRO CLAVEL GARCÍA",
        "voted": false
    },
    {
        "code": 20275518,
        "name": " ELIAS ERNESTO LEMUS RODRÍGUEZ",
        "voted": false
    },
    {
        "code": 20275519,
        "name": " REYES JOSUE MÉNDEZ ARÉVALO",
        "voted": false
    },
    {
        "code": 20275520,
        "name": " EMMANUEL ALEXANDER MOLINA PORTILLO",
        "voted": false
    },
    {
        "code": 20275522,
        "name": " JONATAN JOSE PORTILLO VÁSQUEZ",
        "voted": false
    },
    {
        "code": 20275523,
        "name": " JOSE JEREMIAS VALLE CLAVEL",
        "voted": false
    },
    {
        "code": 20275526,
        "name": " LUIS ALEXANDER RODRIGUEZ QUIJANO",
        "voted": false
    },
    {
        "code": 20348624,
        "name": " SULEYMI DARISSLEY DIAZ MANCIA",
        "voted": false
    },
    {
        "code": 20348628,
        "name": " GADIEL ISAAC DIAZ MANCIA",
        "voted": false
    },
    {
        "code": 20298823,
        "name": " DAYANA SARAI HERNÁNDEZ TORRES",
        "voted": false
    },
    {
        "code": 20298827,
        "name": " VALERIA NICOLE TREJO LEMUS",
        "voted": false
    },
    {
        "code": 20373989,
        "name": " FRANKLIN ANTONIO PORTILLO ALVARADO",
        "voted": false
    },
    {
        "code": 20373990,
        "name": " JOSÉ SANTIAGO PORTILLO RAMÍREZ",
        "voted": false
    },
    {
        "code": 20373992,
        "name": " JOSE ENRIQUE LOPEZ ESTRADA",
        "voted": false
    },
    {
        "code": 20373993,
        "name": " WILMER ALEXANDER MENJÍVAR GIRÓN",
        "voted": false
    },
    {
        "code": 20373997,
        "name": " VICTOR ANTONIO DERAS VASQUEZ",
        "voted": false
    },
    {
        "code": 20373999,
        "name": " JOSE ALEXANDER HERNANDEZ AREVALO",
        "voted": false
    },
    {
        "code": 20374000,
        "name": " ALEXIS ADONAY HERNÁNDEZ HERNÁNDEZ",
        "voted": false
    },
    {
        "code": 20374001,
        "name": " STEVEN VLADIMIR HERNÁNDEZ MENJIVAR",
        "voted": false
    },
    {
        "code": 20374003,
        "name": " JUAN JOSE ORELLANA ALVARADO",
        "voted": false
    },
    {
        "code": 20374006,
        "name": " DARIANA MAYERLI PORTILLO MONTES",
        "voted": false
    },
    {
        "code": 20374008,
        "name": " JOHANNA ESTEFANY RAMIREZ RIVERA",
        "voted": false
    },
    {
        "code": 20374010,
        "name": " DIANA ALESSANDRA SANCHEZ ANAYA",
        "voted": false
    },
    {
        "code": 20374031,
        "name": " DAVID ALEXANDER RIVERA ALVARADO",
        "voted": false
    },
    {
        "code": 20339358,
        "name": " ASHLIE GRACIELA ALEMAN TOBIAS",
        "voted": false
    },
    {
        "code": 20355350,
        "name": " GENESIS CAMILA ZOMETA MENJIVAR",
        "voted": false
    },
    {
        "code": 20398112,
        "name": " DELMY SUGEY MURCIA RODRIGUEZ",
        "voted": false
    },
    {
        "code": 10042100,
        "name": " MARCOS ANTONIO LAINEZ RAMOS",
        "voted": false
    },
    {
        "code": 10093930,
        "name": " ANTHONY ERNESTO MALDONADO CORDOVA",
        "voted": false
    },
    {
        "code": 10118697,
        "name": " ORLANDO OSMÍN IBÁÑEZ PÉREZ",
        "voted": false
    },
    {
        "code": 10154089,
        "name": " CAMILA MARCELA GARCIA MURCIA",
        "voted": false
    },
    {
        "code": 10154498,
        "name": " ALEJANDRA YANETH GONZÁLEZ VALENCIA",
        "voted": false
    },
    {
        "code": 10154573,
        "name": " NICOL CAROLINA GUTIÉRREZ MEJÍA",
        "voted": false
    },
    {
        "code": 10154594,
        "name": " NATASHA GABRIELA HERNÁNDEZ RODRÍGUEZ",
        "voted": false
    },
    {
        "code": 10154773,
        "name": " JOSE GODOFREDO MEJIA PEREZ",
        "voted": false
    },
    {
        "code": 10154818,
        "name": " VALERIA DESIREE ORELLANA ANAYA",
        "voted": false
    },
    {
        "code": 10154902,
        "name": " ANDERSON GAEL RIVAS MANCIA",
        "voted": false
    },
    {
        "code": 10154913,
        "name": " RUTH NOEMI VASQUEZ HENRIQUEZ",
        "voted": false
    },
    {
        "code": 10155402,
        "name": " YUNY JOSUE DURAN HERNANDEZ",
        "voted": false
    },
    {
        "code": 10155427,
        "name": " JOSUE EMILIO FUENTES GUARDADO",
        "voted": false
    },
    {
        "code": 10155550,
        "name": " EDWIN GEOVANNY MARTINEZ DIAZ",
        "voted": false
    },
    {
        "code": 10155577,
        "name": " MADISON JOHENY MENJIVAR PEREZ",
        "voted": false
    },
    {
        "code": 10155795,
        "name": " AMBERLYN MILAGROS ALVARENGA LANDAVERDE",
        "voted": false
    },
    {
        "code": 10156678,
        "name": " BRANDON ANTONIO AGUILAR ARGUMEDO",
        "voted": false
    },
    {
        "code": 10156710,
        "name": " MARCELA YAMILETH ALVARADO RAMIREZ",
        "voted": false
    },
    {
        "code": 10156751,
        "name": " ARIELA JOHANA CARTAGENA ROSA",
        "voted": false
    },
    {
        "code": 10156770,
        "name": " BYRON ALEXANDER MENJÍVAR DÍAZ",
        "voted": false
    },
    {
        "code": 10156784,
        "name": " JOHAN RICARDO DIAZ MURCIA",
        "voted": false
    },
    {
        "code": 10156802,
        "name": " MELANY ARIEL ESCALÓN FLORES",
        "voted": false
    },
    {
        "code": 10156847,
        "name": " JOSE ABRAHAN FRANCO PORTILLO",
        "voted": false
    },
    {
        "code": 10156862,
        "name": " VERONICA ELIZABETH GUTIERREZ OSEGUEDA",
        "voted": false
    },
    {
        "code": 10158587,
        "name": " RICARDO JAVIER PEREZ ERAZO",
        "voted": false
    },
    {
        "code": 10158629,
        "name": " KELVIN DANIEL SALGUERO PEREZ",
        "voted": false
    },
    {
        "code": 10161943,
        "name": " MARVIN ALFONSO HERNÁNDEZ HERNÁNDEZ",
        "voted": false
    },
    {
        "code": 10199853,
        "name": " MELANY BREIGGETT ALAS SOLÓRZANO",
        "voted": false
    },
    {
        "code": 10199921,
        "name": " STEVEN ALEXANDER HERNÁNDEZ SANTAMARÍA",
        "voted": false
    },
    {
        "code": 10210518,
        "name": " ROBERTO CARLOS QUIJADA MANCÍA",
        "voted": false
    },
    {
        "code": 10213209,
        "name": " LILY ALINA FRANCO PORTILLO",
        "voted": false
    },
    {
        "code": 10259314,
        "name": " JOSE ANTONIO QUIJADA MANCIA",
        "voted": false
    },
    {
        "code": 10283258,
        "name": " JAVIER ALEXANDER RAMIREZ MEJIA",
        "voted": false
    },
    {
        "code": 10283282,
        "name": " MARIA GUADALUPE ROMERO LANDAVERDE",
        "voted": false
    },
    {
        "code": 10283320,
        "name": " MARIA ALEJANDRA SANTOS VASQUEZ",
        "voted": false
    },
    {
        "code": 10283344,
        "name": " ALAN ESAU SALAS RIVERA",
        "voted": false
    },
    {
        "code": 10283656,
        "name": " ALISSON LILIANA BURGOS PORTILLO",
        "voted": false
    },
    {
        "code": 10292124,
        "name": " JOSÉ LUIS DERAS HERNÁNDEZ",
        "voted": false
    },
    {
        "code": 10293594,
        "name": " EMERSON NAHÚN HERNÁNDEZ ARÉVALO",
        "voted": false
    },
    {
        "code": 10294290,
        "name": " DYLAN ENMANUEL PORTILLO SOLÓRZANO",
        "voted": false
    },
    {
        "code": 10304956,
        "name": " JOSUE ISAIAS CAMPOS ORTIZ",
        "voted": false
    },
    {
        "code": 10305355,
        "name": " ELMER FRANCISCO FUENTES HENRIQUEZ",
        "voted": false
    },
    {
        "code": 10305397,
        "name": " BRANDON ANTONIO FUNES RUMALDO",
        "voted": false
    },
    {
        "code": 10305469,
        "name": " MADALY MICEL MÉNDEZ ARÉVALO",
        "voted": false
    },
    {
        "code": 10305490,
        "name": " JEIMY DAMARIS PÉREZ MARTÍNEZ",
        "voted": false
    },
    {
        "code": 10305535,
        "name": " KATHERIN GABRIELA PÉREZ RIVERA",
        "voted": false
    },
    {
        "code": 10305622,
        "name": " ALICIA ANAHÍ PREZA PÉREZ",
        "voted": false
    },
    {
        "code": 10305911,
        "name": " Brandon Ariel Carpio Najarro",
        "voted": false
    },
    {
        "code": 10306657,
        "name": " RAFAEL ENRIQUE GUTIERREZ OSEGUEDA",
        "voted": false
    },
    {
        "code": 10307491,
        "name": " ANDERSON ALESSANDRO ALEMÁN TOBIAS",
        "voted": false
    },
    {
        "code": 10316097,
        "name": " TRANSITO ANTONIO CHAVARRÍA GARCÍA",
        "voted": false
    },
    {
        "code": 10332548,
        "name": " EMMANUEL ALEJANDRO CONTRERAS PAZ",
        "voted": false
    },
    {
        "code": 10344181,
        "name": " NOE EZEQUIEL DIAZ RODRIGUEZ",
        "voted": false
    },
    {
        "code": 10361538,
        "name": " EMERSON STANLEY LOPEZ PORTILLO",
        "voted": false
    },
    {
        "code": 10465166,
        "name": " GENESIS ARLET TEJADA PORTILLO",
        "voted": false
    },
    {
        "code": 10474861,
        "name": " ARLIN ELIZABETH GARCÍA PÉREZ",
        "voted": false
    },
    {
        "code": 10474872,
        "name": " WILBER GIOVANNI GARCÍA RIVERA",
        "voted": false
    },
    {
        "code": 10475025,
        "name": " CARLOS EUGENIO HERNÁNDEZ DÍAZ",
        "voted": false
    },
    {
        "code": 10475071,
        "name": " DILAN ERNESTO MANCIA HERNÁNDEZ",
        "voted": false
    },
    {
        "code": 10475127,
        "name": " LUIS ANTONIO REGALADO OSEGUEDA",
        "voted": false
    },
    {
        "code": 10475153,
        "name": " SAUL EFRAIN RIVERA HERNÁNDEZ",
        "voted": false
    },
    {
        "code": 10480788,
        "name": " ZULMA MONSERRATH ROMERO HERNÁNDEZ",
        "voted": false
    },
    {
        "code": 10484412,
        "name": " ANGIE VALERIA HERNÁNDEZ CALLEJAS",
        "voted": false
    },
    {
        "code": 10499005,
        "name": " JOSE DANIEL PEREZ LINARES",
        "voted": false
    },
    {
        "code": 10499028,
        "name": " ADRIANA ESMERALDA LEON MOLINA",
        "voted": false
    },
    {
        "code": 10521848,
        "name": " ALVARO JOAN MENJÍVAR BONILLA",
        "voted": false
    },
    {
        "code": 10525839,
        "name": " JUAN FELIPE GUTIÉRREZ MEJÍA",
        "voted": false
    },
    {
        "code": 10591519,
        "name": " MARILYN FLORIBETH SOLÓRZANO RECINOS",
        "voted": false
    },
    {
        "code": 10608190,
        "name": " ESTANLEY NICOLAS VASQUEZ MENA",
        "voted": false
    },
    {
        "code": 10608215,
        "name": " KATHERINE SARAI VASQUEZ AVALOS",
        "voted": false
    },
    {
        "code": 10608242,
        "name": " JADIEL BALMORE PEREZ DERAS",
        "voted": false
    },
    {
        "code": 10608334,
        "name": " ENMANUEL ELISEO DÍAZ RODRÍGUEZ",
        "voted": false
    },
    {
        "code": 10608367,
        "name": " GEOVANNY ALEJANDRO FUNES RUMALDO",
        "voted": false
    },
    {
        "code": 10608421,
        "name": " ANGEL EMANUEL ALVARADO PEREZ",
        "voted": false
    },
    {
        "code": 10608468,
        "name": " ULISES BENJAMIN DURAN HERNANDEZ",
        "voted": false
    },
    {
        "code": 10608520,
        "name": " EDUARDO BLADIMIR ESCALON FLORES",
        "voted": false
    },
    {
        "code": 10608625,
        "name": " JOHANA BEATRIZ MENJIVAR GIRON",
        "voted": false
    },
    {
        "code": 10608678,
        "name": " LUCERO SARAI OCHOA MOLINA",
        "voted": false
    },
    {
        "code": 10620993,
        "name": " MELVIN OMAR FUNES SALGUERO",
        "voted": false
    },
    {
        "code": 10621005,
        "name": " SAUL BENJAMIN MURCIA HERNANDEZ",
        "voted": false
    },
    {
        "code": 10621068,
        "name": " SOFIA ISABELLA VALENCIA DAMAS",
        "voted": false
    },
    {
        "code": 10621102,
        "name": " MADELIN ALEXA PREZA PEREZ",
        "voted": false
    },
    {
        "code": 10621118,
        "name": " NAHUN ISAIAS FRANCO DERAS",
        "voted": false
    },
    {
        "code": 10621202,
        "name": " FABIO EMANUEL OSEGUEDA CARDOZA",
        "voted": false
    },
    {
        "code": 10621224,
        "name": " KEVIN ADONAY CORDOVA MEJIA",
        "voted": false
    },
    {
        "code": 10621234,
        "name": " IMMER ANDRES DIAZ MURCIA",
        "voted": false
    },
    {
        "code": 10621249,
        "name": " CRISTIAN DANIEL HUEZO OSEGUEDA",
        "voted": false
    },
    {
        "code": 10621278,
        "name": " JULIA ISABEL LANDAVERDE VASQUEZ",
        "voted": false
    },
    {
        "code": 10621317,
        "name": " MOISES EMMANUEL SALGUERO PEREZ",
        "voted": false
    },
    {
        "code": 10621338,
        "name": " MADELINE ADRIANA LANDAVERDE SUBVADO",
        "voted": false
    },
    {
        "code": 10621384,
        "name": " AMY SOFÍA MURCIA ALAS",
        "voted": false
    },
    {
        "code": 10626960,
        "name": " JUSTIN ALAN SÁNCHEZ RAMÍREZ",
        "voted": false
    },
    {
        "code": 10627294,
        "name": " DYLAN ANDRES ARTEAGA GARCIA",
        "voted": false
    },
    {
        "code": 10670222,
        "name": " Rodrigo Emanuel Sevillano Flores",
        "voted": false
    },
    {
        "code": 10674948,
        "name": " SOFIA GUADALUPE QUIJADA ZAMORA",
        "voted": false
    },
    {
        "code": 10674959,
        "name": " ISIS VERONICA PEREZ ALAS",
        "voted": false
    },
    {
        "code": 10687204,
        "name": " René Alexander Gutiérrez Estrada",
        "voted": false
    },
    {
        "code": 10721020,
        "name": " JOSÉ EZEQUIEL LANDAVERDE SUBVADO",
        "voted": false
    },
    {
        "code": 10721033,
        "name": " ARIANA MONSERRAT HERNANDEZ RODRIGUEZ",
        "voted": false
    },
    {
        "code": 10721054,
        "name": " VALERIA NOEMY MANCIA DIAZ",
        "voted": false
    },
    {
        "code": 10721202,
        "name": " MADELIN DANIELA CLAVEL GARCÍA",
        "voted": false
    },
    {
        "code": 10721269,
        "name": " KEVIN DANIEL MEJÍA PEREZ",
        "voted": false
    },
    {
        "code": 10721355,
        "name": " JEFERSON ALEXIS VILLANUEVA RIVERA",
        "voted": false
    },
    {
        "code": 10739095,
        "name": " EMELY CRISBELL VALLE GUARDADO",
        "voted": false
    },
    {
        "code": 10739107,
        "name": " KEVIN JOSÉ PORTILLO ALVARADO",
        "voted": false
    },
    {
        "code": 10739114,
        "name": " EDUARDO ULISES LEÓN MOLINA",
        "voted": false
    },
    {
        "code": 10739129,
        "name": " MATEO ALEXANDER CUELLAR HERNÁNDEZ",
        "voted": false
    },
    {
        "code": 10739154,
        "name": " AMY GISELLE BONILLA AGUILAR",
        "voted": false
    },
    {
        "code": 10739169,
        "name": " EMELY CATALINA ALVARADO FLORES",
        "voted": false
    },
    {
        "code": 10786866,
        "name": " NATHALY LISSBETH RIVAS MANCIA",
        "voted": false
    },
    {
        "code": 10803556,
        "name": " ELMER ISAAC SALGUERO BAIRES",
        "voted": false
    },
    {
        "code": 10803584,
        "name": " JOSUÉ ISAIAS PINEDA CORTEZ",
        "voted": false
    },
    {
        "code": 10806820,
        "name": " JUAN ANTONIO CASTRO RAMÍREZ",
        "voted": false
    },
    {
        "code": 10821220,
        "name": " JOSIAS ABEL TEJADA RAMÍREZ",
        "voted": false
    },
    {
        "code": 10868619,
        "name": " ALLISON STACY FUNES RUMALDO",
        "voted": false
    },
    {
        "code": 10868631,
        "name": " GENESIS ABIGAIL LÓPEZ ESTRADA",
        "voted": false
    },
    {
        "code": 10868649,
        "name": " MILAGRO ZULEMA MURCIA HERNÁNDEZ",
        "voted": false
    },
    {
        "code": 10868659,
        "name": " JORGE ALEXANDER PAZ GUARDADO",
        "voted": false
    },
    {
        "code": 10868668,
        "name": " ANDREA SOFIA PÉREZ HERNÁNDEZ",
        "voted": false
    },
    {
        "code": 10868693,
        "name": " GENESIS ESTER PÉREZ MARTÍNEZ",
        "voted": false
    },
    {
        "code": 10868707,
        "name": " ANTHONY JEREMIAS PÉREZ PÉREZ",
        "voted": false
    },
    {
        "code": 10868724,
        "name": " DAILYN ZOE LAÍNEZ ESTRADA",
        "voted": false
    },
    {
        "code": 10868768,
        "name": " KEVIN JOSUE FUENTES HERNRIQUEZ",
        "voted": false
    },
    {
        "code": 10868779,
        "name": " MOISES CRISTOBAL LANDAVERDE GUILLEN",
        "voted": false
    },
    {
        "code": 10868793,
        "name": " ESTEFANY CAROLINA LANDAVERDE REYES",
        "voted": false
    },
    {
        "code": 10870351,
        "name": " ALVARO EFRAIN MARTINEZ DERAS",
        "voted": false
    },
    {
        "code": 10870371,
        "name": " ERICK MATEO MEJIA CARBAJAL",
        "voted": false
    },
    {
        "code": 10870390,
        "name": " DAVID ALEJANDRO OCHOA ALFARO",
        "voted": false
    },
    {
        "code": 10870403,
        "name": " WILLIAM DANIEL ORELLANA ALVARADO",
        "voted": false
    },
    {
        "code": 10870423,
        "name": " FABRICIO ALEJANDRO OSEGUEDA PÉREZ",
        "voted": false
    },
    {
        "code": 10870452,
        "name": " YERIK ZAID GUILLEN SORTO",
        "voted": false
    },
    {
        "code": 10870469,
        "name": " JOSÉ ELISEO MARTINEZ ARTIGA",
        "voted": false
    },
    {
        "code": 10870481,
        "name": " RAFAEL ALEXANDER ANAYA CORTEZ",
        "voted": false
    },
    {
        "code": 10870839,
        "name": " MARJORY ALEXANDRA AVELAR RIVERA",
        "voted": false
    },
    {
        "code": 10870864,
        "name": " GAMALIEL BENJAMIN GUTIERREZ BACA",
        "voted": false
    },
    {
        "code": 10873521,
        "name": " DIMAS MAURICIO HERNÁNDEZ HERNÁNDEZ",
        "voted": false
    },
    {
        "code": 10882409,
        "name": " RUTH EUNICE MARIN LOPEZ",
        "voted": false
    },
    {
        "code": 10917850,
        "name": " SAHILY ALESSANDRA ALAS VENTURA",
        "voted": false
    },
    {
        "code": 10935029,
        "name": " Brayan Alberto Rivas Carpio",
        "voted": false
    },
    {
        "code": 10948274,
        "name": " RONY YOHAN CORTEZ ROMERO",
        "voted": false
    },
    {
        "code": 10972600,
        "name": " JANNELI SARAHI GUTIERREZ BACA",
        "voted": false
    },
    {
        "code": 10996803,
        "name": " RAUL MATEO ECHEVERRÍA MANCIA",
        "voted": false
    },
    {
        "code": 10999686,
        "name": " ALICIA ISABELLA NUÑEZ OSEGUEDA",
        "voted": false
    },
    {
        "code": 10999766,
        "name": " SAMUEL ISAAC OSEGUEDA CARDOZA",
        "voted": false
    },
    {
        "code": 10999782,
        "name": " EDENILSON JONATHAN HERNANDEZ ORTIZ",
        "voted": false
    },
    {
        "code": 10999802,
        "name": " SEBASTIAN RAFAEL TEJADA PORTILLO",
        "voted": false
    },
    {
        "code": 10999838,
        "name": " DENIS ALEJANDRO AVELAR PORTILLO",
        "voted": false
    },
    {
        "code": 10999852,
        "name": " STANLEY DE JESUS MENJIVAR ESCALON",
        "voted": false
    },
    {
        "code": 10999866,
        "name": " CRISTOFER CALEB DERAS FLORES",
        "voted": false
    },
    {
        "code": 10999897,
        "name": " DOUGLAS EZEQUIEL ROMERO LANDAVERDE",
        "voted": false
    },
    {
        "code": 10999916,
        "name": " ADRIANA FABIOLA DIAZ CARDOZA",
        "voted": false
    },
    {
        "code": 10999958,
        "name": " CRISTOBAL ANTONIO CONTRERAS PAZ",
        "voted": false
    },
    {
        "code": 11027300,
        "name": " XIMENA ALICIA GARCÍA PÉREZ",
        "voted": false
    },
    {
        "code": 11055694,
        "name": " ALISON BERENISE REINA BORJA",
        "voted": true
    },
    {
        "code": 11076594,
        "name": " JOSUE ALEXIS PINEDA ALVARADO",
        "voted": true
    }
]